LICENSE.rst
MANIFEST.in
README.rst
setup.cfg
setup.py
backports/__init__.py
backports/inspect.py
backports.inspect.egg-info/PKG-INFO
backports.inspect.egg-info/SOURCES.txt
backports.inspect.egg-info/dependency_links.txt
backports.inspect.egg-info/namespace_packages.txt
backports.inspect.egg-info/pbr.json
backports.inspect.egg-info/requires.txt
backports.inspect.egg-info/top_level.txt