Metadata-Version: 1.1
Name: backports.inspect
Version: 0.0.3
Summary: Backport (some) Python 3 `inspect` module features to 2.7 (extending aliles/funcsigs)
Home-page: https://github.com/agoraplex/backports.inspect
Author: Tripp Lilley
Author-email: tripplilley@gmail.com
License: BSD
Platform: UNKNOWN
Classifier: Development Status :: 3 - Alpha
Classifier: Intended Audience :: Developers
Classifier: Operating System :: OS Independent
Classifier: Programming Language :: Python :: 2.7
Classifier: Topic :: Software Development :: Libraries :: Python Modules
